LICENSE.txt
README.md
setup.py
asBASE/__init__.py
asBASE.egg-info/PKG-INFO
asBASE.egg-info/SOURCES.txt
asBASE.egg-info/dependency_links.txt
asBASE.egg-info/top_level.txt