Metadata-Version: 2.1
Name: asBASE
Version: 0.4
Summary: With this library, You can store json easily and smoothly with many features
Author: VIRUS
Classifier: Programming Language :: Python :: 3
Classifier: Operating System :: OS Independent
Classifier: License :: OSI Approved :: MIT License
License-File: LICENSE.txt
